README
setup.py
remarkuple/__init__.py
remarkuple/main.py
remarkuple/svg.py
remarkuple/table.py
remarkuple.egg-info/PKG-INFO
remarkuple.egg-info/SOURCES.txt
remarkuple.egg-info/dependency_links.txt
remarkuple.egg-info/top_level.txt