Metadata-Version: 1.1
Name: remarkuple
Version: 0.1.2
Summary: Remarkuple - XML/HTML/SVG tag generation helper for Python
Home-page: https://github.com/markomanninen/remarkuple
Author: Marko Manninen
Author-email: elonmedia@gmail.com
License: UNKNOWN
Download-URL: https://github.com/markomanninen/remarkuple/archive/v0.1.2.tar.gz
Keywords: python,jupyter notebook,html,xml,xhtml,svg
Platform: any
Classifier: Development Status :: 3 - Alpha
Classifier: Intended Audience :: Developers
Classifier: License :: OSI Approved :: MIT License
Classifier: Operating System :: OS Independent
Classifier: Programming Language :: Python
Classifier: Topic :: Software Development :: Libraries
